qiskit_ibm_transpiler/__init__.py
qiskit_ibm_transpiler/ai_passmanager.py
qiskit_ibm_transpiler/transpiler_service.py
qiskit_ibm_transpiler/types.py
qiskit_ibm_transpiler/utils.py
qiskit_ibm_transpiler/version.py
qiskit_ibm_transpiler/ai/__init__.py
qiskit_ibm_transpiler/ai/collection.py
qiskit_ibm_transpiler/ai/routing.py
qiskit_ibm_transpiler/ai/synthesis.py
qiskit_ibm_transpiler/wrappers/__init__.py
qiskit_ibm_transpiler/wrappers/ai_api_routing.py
qiskit_ibm_transpiler/wrappers/ai_api_synthesis.py
qiskit_ibm_transpiler/wrappers/ai_local_routing.py
qiskit_ibm_transpiler/wrappers/ai_local_synthesis.py
qiskit_ibm_transpiler/wrappers/base.py
qiskit_ibm_transpiler/wrappers/function_transpile.py
qiskit_ibm_transpiler/wrappers/transpile.py
qiskit_ibm_transpiler-0.15.2.dist-info/licenses/LICENSE
qiskit_ibm_transpiler-0.15.2.dist-info/METADATA
qiskit_ibm_transpiler-0.15.2.dist-info/WHEEL
qiskit_ibm_transpiler-0.15.2.dist-info/top_level.txt
qiskit_ibm_transpiler-0.15.2.dist-info/RECORD
