Metadata-Version: 2.4
Name: qiskit-ibm-transpiler
Version: 0.15.2
Summary: A library to use Qiskit IBM Transpiler (https://quantum.cloud.ibm.com/docs/api/qiskit-ibm-transpiler) and the AI transpiler passes (https://quantum.cloud.ibm.com/docs/guides/ai-transpiler-passes)
Author: Qiskit Development Team
License: Apache-2.0
Project-URL: Bug Tracker, https://github.com/Qiskit/qiskit-ibm-transpiler/issues
Project-URL: Documentation, https://github.com/Qiskit/qiskit-ibm-transpiler
Project-URL: Source Code, https://github.com/Qiskit/qiskit-ibm-transpiler
Keywords: qiskit,ai,transpiler,routing
Classifier: Environment :: Console
Classifier: License :: OSI Approved :: Apache Software License
Classifier: Intended Audience :: Developers
Classifier: Intended Audience :: Science/Research
Classifier: Operating System :: Microsoft :: Windows
Classifier: Operating System :: MacOS
Classifier: Operating System :: POSIX :: Linux
Classifier: Programming Language :: Python :: 3.10
Classifier: Programming Language :: Python :: 3.11
Classifier: Programming Language :: Python :: 3.12
Classifier: Programming Language :: Python :: 3.13
Classifier: Topic :: Scientific/Engineering
Requires-Python: <3.14,>=3.10
License-File: LICENSE
Requires-Dist: qiskit<3.0.0,>=1.4.2
Requires-Dist: backoff~=2.0
Requires-Dist: qiskit-qasm3-import~=0.4
Requires-Dist: requests~=2.0
Requires-Dist: networkx==2.8.5
Requires-Dist: qiskit-serverless~=0.28.0
Requires-Dist: qiskit_ibm_ai_local_transpiler~=0.5
Provides-Extra: ai-local-mode
Dynamic: license-file
